python_simple_rules_engine/__init__.py
python_simple_rules_engine-1.0.0.dist-info/LICENSE.txt
python_simple_rules_engine-1.0.0.dist-info/METADATA
python_simple_rules_engine-1.0.0.dist-info/WHEEL
python_simple_rules_engine-1.0.0.dist-info/top_level.txt
python_simple_rules_engine-1.0.0.dist-info/RECORD
