Metadata-Version: 2.1
Name: python-simple-rules-engine
Version: 1.0.0
Summary: Evaluate rules based on a subject
Home-page: https://github.com/rogervila/python_simple_rules_engine
Download-URL: https://github.com/rogervila/python_simple_rules_engine/archive/1.0.0.tar.gz
Author: Roger Vilà
Author-email: rogervila@me.com
License: MIT
Keywords: python rules engine
Classifier: Development Status :: 5 - Production/Stable
Classifier: Intended Audience :: Developers
Classifier: Topic :: Software Development :: Build Tools
Classifier: License :: OSI Approved :: MIT License
Classifier: Programming Language :: Python :: 3.9
License-File: LICENSE.txt
